pyquizrd/__init__.py
pyquizrd/gpt/__init__.py
pyquizrd/gpt/gpt.py
pyquizrd/gpt/prompt.txt
pyquizrd/gpt/x.py
pyquizrd/jeopardy/__init__.py
pyquizrd/jeopardy/jeopardy.py
pyquizrd/jeopardy/pruned_jeopardy.json
pyquizrd/jeopardy/pruned_jeopardy.json.Z
pyquizrd/manual/__init__.py
pyquizrd/manual/manual.py
pyquizrd/opentrivia/__init__.py
pyquizrd/opentrivia/opentrivia.py
pyquizrd/palm/__init__.py
pyquizrd/palm/palm.py
pyquizrd/palm/prompt.txt
pyquizrd/pyquizrd.py
pyquizrd-0.1.6.dist-info/METADATA
pyquizrd-0.1.6.dist-info/WHEEL
pyquizrd-0.1.6.dist-info/RECORD
