Metadata-Version: 2.1
Name: pyquizrd
Version: 0.1.6
Summary: 
Author: marcacohen
Author-email: marcacohen@gmail.com
Requires-Python: >=3.11,<4.0
Classifier: Programming Language :: Python :: 3
Classifier: Programming Language :: Python :: 3.11
Requires-Dist: langchain (>=0.0.240,<0.0.241)
